versiongit/__init__.py
versiongit/_version_git.py
versiongit/command.py
versiongit-2.2.dist-info/LICENSE
versiongit-2.2.dist-info/METADATA
versiongit-2.2.dist-info/WHEEL
versiongit-2.2.dist-info/entry_points.txt
versiongit-2.2.dist-info/top_level.txt
versiongit-2.2.dist-info/RECORD
