Metadata-Version: 2.1
Name: versiongit
Version: 2.2
Summary: Tool for adding version from git to a python project without adding dependencies
Home-page: https://github.com/dls-controls/versiongit
Author: Tom Cobb
Author-email: tom.cobb@diamond.ac.uk
License: CC0 1.0
Platform: UNKNOWN
Classifier: Development Status :: 5 - Production/Stable
Classifier: License :: CC0 1.0 Universal (CC0 1.0) Public Domain Dedication
Classifier: Programming Language :: Python :: 3.6
Classifier: Programming Language :: Python :: 3.7
Classifier: Programming Language :: Python :: 3.8
Classifier: Programming Language :: Python :: 3.9
